main.py
src/__ init __.py
src/pypscloud.py
pypscloud-0.0.4.dist-info/METADATA
pypscloud-0.0.4.dist-info/WHEEL
pypscloud-0.0.4.dist-info/licenses/LICENSE
pypscloud-0.0.4.dist-info/RECORD
