Metadata-Version: 2.1
Name: pypscloud
Version: 0.0.4
Summary: Common wrappers and tools for the Powerside Cloud API
Project-URL: Homepage, https://github.com/powerstandards/pypscloud
Project-URL: Bug Tracker, https://github.com/powerstandards/pypscloud/issues
Author-email: Louis Marchand <louis.marchand@powerside.com>
License-File: LICENSE
Classifier: License :: OSI Approved :: MIT License
Classifier: Operating System :: OS Independent
Classifier: Programming Language :: Python :: 3
Requires-Python: >=3.8
